{
	"name": "ds_source_newtable",
	"properties": {
		"linkedServiceName": {
			"referenceName": "ls_adls",
			"type": "LinkedServiceReference"
		},
		"parameters": {
			"Filename": {
				"type": "string"
			}
		},
		"folder": {
			"name": "Pooja"
		},
		"annotations": [],
		"type": "DelimitedText",
		"typeProperties": {
			"location": {
				"type": "AzureBlobFSLocation",
				"fileName": {
					"value": "@dataset().Filename",
					"type": "Expression"
				},
				"fileSystem": "destination"
			},
			"columnDelimiter": ",",
			"escapeChar": "\\",
			"firstRowAsHeader": true,
			"quoteChar": "\""
		},
		"schema": []
	}
}